{
  "updated": "2026-04-16T14:15:48.143Z",
  "series": {
    "DGS10": {
      "value": 4.26,
      "date": "2026-04-14",
      "prev": 4.3,
      "chg": -0.04,
      "history": [
        {
          "d": "2026-03-04",
          "v": 4.09
        },
        {
          "d": "2026-03-05",
          "v": 4.13
        },
        {
          "d": "2026-03-06",
          "v": 4.15
        },
        {
          "d": "2026-03-09",
          "v": 4.12
        },
        {
          "d": "2026-03-10",
          "v": 4.15
        },
        {
          "d": "2026-03-11",
          "v": 4.21
        },
        {
          "d": "2026-03-12",
          "v": 4.27
        },
        {
          "d": "2026-03-13",
          "v": 4.28
        },
        {
          "d": "2026-03-16",
          "v": 4.23
        },
        {
          "d": "2026-03-17",
          "v": 4.2
        },
        {
          "d": "2026-03-18",
          "v": 4.26
        },
        {
          "d": "2026-03-19",
          "v": 4.25
        },
        {
          "d": "2026-03-20",
          "v": 4.39
        },
        {
          "d": "2026-03-23",
          "v": 4.34
        },
        {
          "d": "2026-03-24",
          "v": 4.39
        },
        {
          "d": "2026-03-25",
          "v": 4.33
        },
        {
          "d": "2026-03-26",
          "v": 4.42
        },
        {
          "d": "2026-03-27",
          "v": 4.44
        },
        {
          "d": "2026-03-30",
          "v": 4.35
        },
        {
          "d": "2026-03-31",
          "v": 4.3
        },
        {
          "d": "2026-04-01",
          "v": 4.33
        },
        {
          "d": "2026-04-02",
          "v": 4.31
        },
        {
          "d": "2026-04-03",
          "v": 4.35
        },
        {
          "d": "2026-04-06",
          "v": 4.34
        },
        {
          "d": "2026-04-07",
          "v": 4.33
        },
        {
          "d": "2026-04-08",
          "v": 4.29
        },
        {
          "d": "2026-04-09",
          "v": 4.29
        },
        {
          "d": "2026-04-10",
          "v": 4.31
        },
        {
          "d": "2026-04-13",
          "v": 4.3
        },
        {
          "d": "2026-04-14",
          "v": 4.26
        }
      ]
    },
    "DFEDTARU": {
      "value": 3.75,
      "date": "2026-04-16",
      "prev": 3.75,
      "chg": 0,
      "history": [
        {
          "d": "2026-03-18",
          "v": 3.75
        },
        {
          "d": "2026-03-19",
          "v": 3.75
        },
        {
          "d": "2026-03-20",
          "v": 3.75
        },
        {
          "d": "2026-03-21",
          "v": 3.75
        },
        {
          "d": "2026-03-22",
          "v": 3.75
        },
        {
          "d": "2026-03-23",
          "v": 3.75
        },
        {
          "d": "2026-03-24",
          "v": 3.75
        },
        {
          "d": "2026-03-25",
          "v": 3.75
        },
        {
          "d": "2026-03-26",
          "v": 3.75
        },
        {
          "d": "2026-03-27",
          "v": 3.75
        },
        {
          "d": "2026-03-28",
          "v": 3.75
        },
        {
          "d": "2026-03-29",
          "v": 3.75
        },
        {
          "d": "2026-03-30",
          "v": 3.75
        },
        {
          "d": "2026-03-31",
          "v": 3.75
        },
        {
          "d": "2026-04-01",
          "v": 3.75
        },
        {
          "d": "2026-04-02",
          "v": 3.75
        },
        {
          "d": "2026-04-03",
          "v": 3.75
        },
        {
          "d": "2026-04-04",
          "v": 3.75
        },
        {
          "d": "2026-04-05",
          "v": 3.75
        },
        {
          "d": "2026-04-06",
          "v": 3.75
        },
        {
          "d": "2026-04-07",
          "v": 3.75
        },
        {
          "d": "2026-04-08",
          "v": 3.75
        },
        {
          "d": "2026-04-09",
          "v": 3.75
        },
        {
          "d": "2026-04-10",
          "v": 3.75
        },
        {
          "d": "2026-04-11",
          "v": 3.75
        },
        {
          "d": "2026-04-12",
          "v": 3.75
        },
        {
          "d": "2026-04-13",
          "v": 3.75
        },
        {
          "d": "2026-04-14",
          "v": 3.75
        },
        {
          "d": "2026-04-15",
          "v": 3.75
        },
        {
          "d": "2026-04-16",
          "v": 3.75
        }
      ]
    },
    "T10Y2Y": {
      "value": 0.53,
      "date": "2026-04-15",
      "prev": 0.5,
      "chg": 0.03,
      "history": [
        {
          "d": "2026-03-05",
          "v": 0.56
        },
        {
          "d": "2026-03-06",
          "v": 0.59
        },
        {
          "d": "2026-03-09",
          "v": 0.56
        },
        {
          "d": "2026-03-10",
          "v": 0.58
        },
        {
          "d": "2026-03-11",
          "v": 0.57
        },
        {
          "d": "2026-03-12",
          "v": 0.51
        },
        {
          "d": "2026-03-13",
          "v": 0.55
        },
        {
          "d": "2026-03-16",
          "v": 0.55
        },
        {
          "d": "2026-03-17",
          "v": 0.52
        },
        {
          "d": "2026-03-18",
          "v": 0.5
        },
        {
          "d": "2026-03-19",
          "v": 0.46
        },
        {
          "d": "2026-03-20",
          "v": 0.51
        },
        {
          "d": "2026-03-23",
          "v": 0.51
        },
        {
          "d": "2026-03-24",
          "v": 0.49
        },
        {
          "d": "2026-03-25",
          "v": 0.49
        },
        {
          "d": "2026-03-26",
          "v": 0.46
        },
        {
          "d": "2026-03-27",
          "v": 0.56
        },
        {
          "d": "2026-03-30",
          "v": 0.53
        },
        {
          "d": "2026-03-31",
          "v": 0.51
        },
        {
          "d": "2026-04-01",
          "v": 0.52
        },
        {
          "d": "2026-04-02",
          "v": 0.52
        },
        {
          "d": "2026-04-03",
          "v": 0.51
        },
        {
          "d": "2026-04-06",
          "v": 0.5
        },
        {
          "d": "2026-04-07",
          "v": 0.52
        },
        {
          "d": "2026-04-08",
          "v": 0.5
        },
        {
          "d": "2026-04-09",
          "v": 0.51
        },
        {
          "d": "2026-04-10",
          "v": 0.5
        },
        {
          "d": "2026-04-13",
          "v": 0.52
        },
        {
          "d": "2026-04-14",
          "v": 0.5
        },
        {
          "d": "2026-04-15",
          "v": 0.53
        }
      ]
    },
    "DFII10": {
      "value": 1.89,
      "date": "2026-04-14",
      "prev": 1.92,
      "chg": -0.03,
      "history": [
        {
          "d": "2026-03-04",
          "v": 1.8
        },
        {
          "d": "2026-03-05",
          "v": 1.82
        },
        {
          "d": "2026-03-06",
          "v": 1.8
        },
        {
          "d": "2026-03-09",
          "v": 1.78
        },
        {
          "d": "2026-03-10",
          "v": 1.82
        },
        {
          "d": "2026-03-11",
          "v": 1.85
        },
        {
          "d": "2026-03-12",
          "v": 1.89
        },
        {
          "d": "2026-03-13",
          "v": 1.92
        },
        {
          "d": "2026-03-16",
          "v": 1.87
        },
        {
          "d": "2026-03-17",
          "v": 1.83
        },
        {
          "d": "2026-03-18",
          "v": 1.86
        },
        {
          "d": "2026-03-19",
          "v": 1.88
        },
        {
          "d": "2026-03-20",
          "v": 2.01
        },
        {
          "d": "2026-03-23",
          "v": 2.01
        },
        {
          "d": "2026-03-24",
          "v": 2.06
        },
        {
          "d": "2026-03-25",
          "v": 2.02
        },
        {
          "d": "2026-03-26",
          "v": 2.08
        },
        {
          "d": "2026-03-27",
          "v": 2.13
        },
        {
          "d": "2026-03-30",
          "v": 2.04
        },
        {
          "d": "2026-03-31",
          "v": 2
        },
        {
          "d": "2026-04-01",
          "v": 2.02
        },
        {
          "d": "2026-04-02",
          "v": 1.97
        },
        {
          "d": "2026-04-03",
          "v": 1.99
        },
        {
          "d": "2026-04-06",
          "v": 1.98
        },
        {
          "d": "2026-04-07",
          "v": 1.96
        },
        {
          "d": "2026-04-08",
          "v": 1.96
        },
        {
          "d": "2026-04-09",
          "v": 1.95
        },
        {
          "d": "2026-04-10",
          "v": 1.95
        },
        {
          "d": "2026-04-13",
          "v": 1.92
        },
        {
          "d": "2026-04-14",
          "v": 1.89
        }
      ]
    },
    "WM2NS": {
      "value": 22695.9,
      "date": "2026-03-02",
      "prev": 22578.9,
      "chg": 117,
      "history": [
        {
          "d": "2025-08-11",
          "v": 22028.4
        },
        {
          "d": "2025-08-18",
          "v": 22071
        },
        {
          "d": "2025-08-25",
          "v": 21971.9
        },
        {
          "d": "2025-09-01",
          "v": 22060
        },
        {
          "d": "2025-09-08",
          "v": 22139.2
        },
        {
          "d": "2025-09-15",
          "v": 22177
        },
        {
          "d": "2025-09-22",
          "v": 22058
        },
        {
          "d": "2025-09-29",
          "v": 22063
        },
        {
          "d": "2025-10-06",
          "v": 22208.1
        },
        {
          "d": "2025-10-13",
          "v": 22182.2
        },
        {
          "d": "2025-10-20",
          "v": 22207.4
        },
        {
          "d": "2025-10-27",
          "v": 22097
        },
        {
          "d": "2025-11-03",
          "v": 22263.9
        },
        {
          "d": "2025-11-10",
          "v": 22232.5
        },
        {
          "d": "2025-11-17",
          "v": 22292.4
        },
        {
          "d": "2025-11-24",
          "v": 22265.7
        },
        {
          "d": "2025-12-01",
          "v": 22386.9
        },
        {
          "d": "2025-12-08",
          "v": 22416
        },
        {
          "d": "2025-12-15",
          "v": 22500.6
        },
        {
          "d": "2025-12-22",
          "v": 22586.2
        },
        {
          "d": "2025-12-29",
          "v": 22634.6
        },
        {
          "d": "2026-01-05",
          "v": 22646.5
        },
        {
          "d": "2026-01-12",
          "v": 22578.7
        },
        {
          "d": "2026-01-19",
          "v": 22485.3
        },
        {
          "d": "2026-01-26",
          "v": 22385.1
        },
        {
          "d": "2026-02-02",
          "v": 22463.6
        },
        {
          "d": "2026-02-09",
          "v": 22515.2
        },
        {
          "d": "2026-02-16",
          "v": 22565.4
        },
        {
          "d": "2026-02-23",
          "v": 22578.9
        },
        {
          "d": "2026-03-02",
          "v": 22695.9
        }
      ]
    },
    "DTWEXBGS": null,
    "MPMISM": null,
    "TEDRATE": {
      "value": 0.09,
      "date": "2022-01-21",
      "prev": 0.08,
      "chg": 0.01,
      "history": [
        {
          "d": "2021-12-13",
          "v": 0.15
        },
        {
          "d": "2021-12-14",
          "v": 0.16
        },
        {
          "d": "2021-12-15",
          "v": 0.16
        },
        {
          "d": "2021-12-16",
          "v": 0.16
        },
        {
          "d": "2021-12-17",
          "v": 0.16
        },
        {
          "d": "2021-12-20",
          "v": 0.14
        },
        {
          "d": "2021-12-21",
          "v": 0.15
        },
        {
          "d": "2021-12-22",
          "v": 0.13
        },
        {
          "d": "2021-12-23",
          "v": 0.14
        },
        {
          "d": "2021-12-29",
          "v": 0.17
        },
        {
          "d": "2021-12-30",
          "v": 0.16
        },
        {
          "d": "2021-12-31",
          "v": 0.15
        },
        {
          "d": "2022-01-04",
          "v": 0.14
        },
        {
          "d": "2022-01-05",
          "v": 0.14
        },
        {
          "d": "2022-01-06",
          "v": 0.13
        },
        {
          "d": "2022-01-07",
          "v": 0.14
        },
        {
          "d": "2022-01-10",
          "v": 0.11
        },
        {
          "d": "2022-01-11",
          "v": 0.12
        },
        {
          "d": "2022-01-12",
          "v": 0.12
        },
        {
          "d": "2022-01-13",
          "v": 0.12
        },
        {
          "d": "2022-01-14",
          "v": 0.11
        },
        {
          "d": "2022-01-18",
          "v": 0.08
        },
        {
          "d": "2022-01-19",
          "v": 0.09
        },
        {
          "d": "2022-01-20",
          "v": 0.08
        },
        {
          "d": "2022-01-21",
          "v": 0.09
        }
      ]
    },
    "SP500": null,
    "CPIAUCSL": null,
    "DCOILWTICO": {
      "value": 100.72,
      "date": "2026-04-13",
      "prev": 98.34,
      "chg": 2.38,
      "history": [
        {
          "d": "2026-03-03",
          "v": 74.48
        },
        {
          "d": "2026-03-04",
          "v": 74.58
        },
        {
          "d": "2026-03-05",
          "v": 80.88
        },
        {
          "d": "2026-03-06",
          "v": 90.77
        },
        {
          "d": "2026-03-09",
          "v": 94.65
        },
        {
          "d": "2026-03-10",
          "v": 83.71
        },
        {
          "d": "2026-03-11",
          "v": 86.8
        },
        {
          "d": "2026-03-12",
          "v": 95.61
        },
        {
          "d": "2026-03-13",
          "v": 98.48
        },
        {
          "d": "2026-03-16",
          "v": 93.39
        },
        {
          "d": "2026-03-17",
          "v": 96.01
        },
        {
          "d": "2026-03-18",
          "v": 96.12
        },
        {
          "d": "2026-03-19",
          "v": 96.11
        },
        {
          "d": "2026-03-20",
          "v": 98.71
        },
        {
          "d": "2026-03-23",
          "v": 89.33
        },
        {
          "d": "2026-03-24",
          "v": 93.18
        },
        {
          "d": "2026-03-25",
          "v": 91.51
        },
        {
          "d": "2026-03-26",
          "v": 96.18
        },
        {
          "d": "2026-03-27",
          "v": 101.26
        },
        {
          "d": "2026-03-30",
          "v": 104.69
        },
        {
          "d": "2026-03-31",
          "v": 102.86
        },
        {
          "d": "2026-04-01",
          "v": 101.9
        },
        {
          "d": "2026-04-02",
          "v": 113.23
        },
        {
          "d": "2026-04-06",
          "v": 114.01
        },
        {
          "d": "2026-04-07",
          "v": 114.58
        },
        {
          "d": "2026-04-08",
          "v": 96.17
        },
        {
          "d": "2026-04-09",
          "v": 99.62
        },
        {
          "d": "2026-04-10",
          "v": 98.34
        },
        {
          "d": "2026-04-13",
          "v": 100.72
        }
      ]
    },
    "BAMLC0A4CBBB": null,
    "UMCSENT": null,
    "UNRATE": null,
    "GOLDAMGBD228NLBM": null,
    "VIXCLS": null,
    "DGS2": null,
    "BAMLH0A0HYM2": null
  }
}